apple_search_ads/__init__.py
apple_search_ads/client.py
apple_search_ads/exceptions.py
apple_search_ads_client-2.7.1.dist-info/licenses/LICENSE
apple_search_ads_client-2.7.1.dist-info/METADATA
apple_search_ads_client-2.7.1.dist-info/WHEEL
apple_search_ads_client-2.7.1.dist-info/top_level.txt
apple_search_ads_client-2.7.1.dist-info/RECORD
