Metadata-Version: 2.4
Name: apple-search-ads-client
Version: 2.7.1
Summary: A Python client for Apple Search Ads API v5
Home-page: https://github.com/bickster/apple-search-ads-python
Author: Bickster LLC
Author-email: Bickster LLC <support@bickster.com>
License: MIT
Project-URL: Homepage, https://github.com/bickster/apple-search-ads-python
Project-URL: Documentation, https://github.com/bickster/apple-search-ads-python/blob/main/README.md
Project-URL: Repository, https://github.com/bickster/apple-search-ads-python
Project-URL: Issues, https://github.com/bickster/apple-search-ads-python/issues
Keywords: apple,search,ads,api,marketing,advertising,ios,app,store
Classifier: Development Status :: 4 - Beta
Classifier: Intended Audience :: Developers
Classifier: Topic :: Software Development :: Libraries :: Python Modules
Classifier: License :: OSI Approved :: MIT License
Classifier: Programming Language :: Python :: 3
Classifier: Programming Language :: Python :: 3.13
Classifier: Operating System :: OS Independent
Classifier: Topic :: Internet :: WWW/HTTP
Classifier: Topic :: Software Development :: Libraries
Requires-Python: >=3.13
License-File: LICENSE
Requires-Dist: PyJWT>=2.8.0
Requires-Dist: cryptography>=41.0.0
Requires-Dist: requests>=2.31.0
Requires-Dist: pandas>=2.0.0
Requires-Dist: ratelimit>=2.2.1
Requires-Dist: python-dateutil>=2.8.0
Provides-Extra: dev
Requires-Dist: pytest>=7.0.0; extra == "dev"
Requires-Dist: pytest-cov>=4.0.0; extra == "dev"
Requires-Dist: pytest-mock>=3.10.0; extra == "dev"
Requires-Dist: black>=23.0.0; extra == "dev"
Requires-Dist: flake8>=6.0.0; extra == "dev"
Requires-Dist: mypy>=1.0.0; extra == "dev"
Requires-Dist: sphinx>=6.0.0; extra == "dev"
Requires-Dist: sphinx-rtd-theme>=1.0.0; extra == "dev"
Dynamic: author
Dynamic: home-page
Dynamic: license-file
Dynamic: requires-python
